{
  "regret_factor": {
    "histogram": [
      13,
      0,
      5,
      0,
      0,
      375,
      0,
      609,
      0,
      0,
      1001,
      0,
      0,
      72,
      0,
      3032,
      0,
      0,
      187,
      0,
      0,
      2415,
      0,
      172,
      0,
      0,
      0,
      0,
      0,
      0,
      0,
      519,
      0,
      0,
      944,
      0,
      605,
      0,
      0,
      263,
      0,
      0,
      107,
      0,
      136,
      0,
      0,
      3,
      0,
      2
    ],
    "bins": [
      0.0,
      0.019,
      0.038,
      0.056999999999999995,
      0.076,
      0.095,
      0.11399999999999999,
      0.133,
      0.152,
      0.17099999999999999,
      0.19,
      0.209,
      0.22799999999999998,
      0.247,
      0.266,
      0.285,
      0.304,
      0.323,
      0.34199999999999997,
      0.361,
      0.38,
      0.39899999999999997,
      0.418,
      0.437,
      0.45599999999999996,
      0.475,
      0.494,
      0.513,
      0.532,
      0.5509999999999999,
      0.57,
      0.589,
      0.608,
      0.627,
      0.646,
      0.665,
      0.6839999999999999,
      0.703,
      0.722,
      0.741,
      0.76,
      0.779,
      0.7979999999999999,
      0.817,
      0.836,
      0.855,
      0.874,
      0.893,
      0.9119999999999999,
      0.9309999999999999,
      0.95
    ],
    "mean": 0.39362332695984703,
    "std": 0.18536297808147517,
    "skewness": 0.6209608371815261,
    "kurtosis": -0.5068933771165218
  },
  "emotion_joy": {
    "histogram": [
      160,
      17,
      0,
      0,
      6181,
      0,
      1,
      0,
      2029,
      0,
      0,
      0,
      1073,
      0,
      0,
      0,
      279,
      0,
      0,
      0,
      21,
      0,
      1,
      0,
      0,
      516,
      0,
      0,
      0,
      19,
      0,
      0,
      0,
      151,
      0,
      0,
      0,
      10,
      0,
      0,
      0,
      1,
      0,
      0,
      0,
      0,
      0,
      0,
      0,
      1
    ],
    "bins": [
      0.0,
      0.012,
      0.024,
      0.036000000000000004,
      0.048,
      0.06,
      0.07200000000000001,
      0.084,
      0.096,
      0.108,
      0.12,
      0.132,
      0.14400000000000002,
      0.156,
      0.168,
      0.18,
      0.192,
      0.20400000000000001,
      0.216,
      0.228,
      0.24,
      0.252,
      0.264,
      0.276,
      0.28800000000000003,
      0.3,
      0.312,
      0.324,
      0.336,
      0.34800000000000003,
      0.36,
      0.372,
      0.384,
      0.396,
      0.40800000000000003,
      0.42,
      0.432,
      0.444,
      0.456,
      0.468,
      0.48,
      0.492,
      0.504,
      0.516,
      0.528,
      0.54,
      0.552,
      0.5640000000000001,
      0.5760000000000001,
      0.588,
      0.6
    ],
    "mean": 0.09197801147227534,
    "std": 0.07543055189346069,
    "skewness": 2.2509087217995494,
    "kurtosis": 5.161513295211206
  },
  "emotion_anger": {
    "histogram": [
      202,
      5,
      931,
      50,
      0,
      0,
      1520,
      0,
      1,
      0,
      542,
      1,
      3718,
      0,
      0,
      13,
      0,
      0,
      2578,
      0,
      0,
      0,
      0,
      0,
      0,
      620,
      0,
      0,
      0,
      0,
      0,
      171,
      0,
      0,
      0,
      0,
      0,
      101,
      0,
      0,
      0,
      0,
      0,
      3,
      0,
      0,
      0,
      0,
      0,
      4
    ],
    "bins": [
      0.0,
      0.008,
      0.016,
      0.024,
      0.032,
      0.04,
      0.048,
      0.056,
      0.064,
      0.07200000000000001,
      0.08,
      0.088,
      0.096,
      0.10400000000000001,
      0.112,
      0.12,
      0.128,
      0.136,
      0.14400000000000002,
      0.152,
      0.16,
      0.168,
      0.176,
      0.184,
      0.192,
      0.2,
      0.20800000000000002,
      0.216,
      0.224,
      0.232,
      0.24,
      0.248,
      0.256,
      0.264,
      0.272,
      0.28,
      0.28800000000000003,
      0.296,
      0.304,
      0.312,
      0.32,
      0.328,
      0.336,
      0.34400000000000003,
      0.352,
      0.36,
      0.368,
      0.376,
      0.384,
      0.392,
      0.4
    ],
    "mean": 0.10510994263862333,
    "std": 0.05624802827728943,
    "skewness": 0.5800854002772713,
    "kurtosis": 0.9405496233515671
  },
  "emotion_surprise": {
    "histogram": [
      59,
      1,
      0,
      410,
      0,
      0,
      112,
      830,
      0,
      194,
      0,
      3859,
      0,
      1,
      0,
      2409,
      78,
      0,
      0,
      1966,
      0,
      1,
      0,
      156,
      1,
      0,
      333,
      0,
      0,
      0,
      14,
      0,
      0,
      0,
      35,
      0,
      0,
      0,
      0,
      0,
      0,
      0,
      0,
      0,
      0,
      0,
      0,
      0,
      0,
      1
    ],
    "bins": [
      0.0,
      0.013000000000000001,
      0.026000000000000002,
      0.03900000000000001,
      0.052000000000000005,
      0.065,
      0.07800000000000001,
      0.09100000000000001,
      0.10400000000000001,
      0.117,
      0.13,
      0.14300000000000002,
      0.15600000000000003,
      0.169,
      0.18200000000000002,
      0.195,
      0.20800000000000002,
      0.22100000000000003,
      0.234,
      0.24700000000000003,
      0.26,
      0.273,
      0.28600000000000003,
      0.29900000000000004,
      0.31200000000000006,
      0.325,
      0.338,
      0.35100000000000003,
      0.36400000000000005,
      0.37700000000000006,
      0.39,
      0.403,
      0.41600000000000004,
      0.42900000000000005,
      0.44200000000000006,
      0.455,
      0.468,
      0.48100000000000004,
      0.49400000000000005,
      0.507,
      0.52,
      0.533,
      0.546,
      0.559,
      0.5720000000000001,
      0.5850000000000001,
      0.5980000000000001,
      0.6110000000000001,
      0.6240000000000001,
      0.637,
      0.65
    ],
    "mean": 0.18080401529636714,
    "std": 0.06597738345282296,
    "skewness": 0.5020345822228767,
    "kurtosis": 1.297645513807418
  },
  "emotion_disgust": {
    "histogram": [
      499,
      0,
      0,
      42,
      0,
      163,
      1,
      0,
      5088,
      0,
      1,
      266,
      0,
      714,
      0,
      0,
      2140,
      0,
      0,
      0,
      167,
      6,
      0,
      1,
      0,
      852,
      0,
      0,
      0,
      0,
      2,
      0,
      0,
      426,
      0,
      0,
      0,
      0,
      1,
      0,
      0,
      68,
      0,
      0,
      0,
      0,
      1,
      0,
      0,
      22
    ],
    "bins": [
      0.0,
      0.006,
      0.012,
      0.018000000000000002,
      0.024,
      0.03,
      0.036000000000000004,
      0.042,
      0.048,
      0.054,
      0.06,
      0.066,
      0.07200000000000001,
      0.078,
      0.084,
      0.09,
      0.096,
      0.10200000000000001,
      0.108,
      0.114,
      0.12,
      0.126,
      0.132,
      0.138,
      0.14400000000000002,
      0.15,
      0.156,
      0.162,
      0.168,
      0.17400000000000002,
      0.18,
      0.186,
      0.192,
      0.198,
      0.20400000000000001,
      0.21,
      0.216,
      0.222,
      0.228,
      0.234,
      0.24,
      0.246,
      0.252,
      0.258,
      0.264,
      0.27,
      0.276,
      0.28200000000000003,
      0.28800000000000003,
      0.294,
      0.3
    ],
    "mean": 0.07728489483747612,
    "std": 0.046735179053113814,
    "skewness": 1.3135332600595813,
    "kurtosis": 2.2223350806597306
  },
  "emotion_sadness": {
    "histogram": [
      9,
      6,
      0,
      122,
      0,
      1,
      10,
      500,
      0,
      16,
      2,
      1026,
      0,
      20,
      0,
      3522,
      36,
      14,
      0,
      2051,
      0,
      109,
      0,
      1860,
      5,
      0,
      984,
      0,
      0,
      0,
      75,
      0,
      1,
      0,
      86,
      0,
      0,
      0,
      1,
      0,
      0,
      0,
      1,
      0,
      0,
      0,
      1,
      0,
      0,
      2
    ],
    "bins": [
      0.0,
      0.013000000000000001,
      0.026000000000000002,
      0.03900000000000001,
      0.052000000000000005,
      0.065,
      0.07800000000000001,
      0.09100000000000001,
      0.10400000000000001,
      0.117,
      0.13,
      0.14300000000000002,
      0.15600000000000003,
      0.169,
      0.18200000000000002,
      0.195,
      0.20800000000000002,
      0.22100000000000003,
      0.234,
      0.24700000000000003,
      0.26,
      0.273,
      0.28600000000000003,
      0.29900000000000004,
      0.31200000000000006,
      0.325,
      0.338,
      0.35100000000000003,
      0.36400000000000005,
      0.37700000000000006,
      0.39,
      0.403,
      0.41600000000000004,
      0.42900000000000005,
      0.44200000000000006,
      0.455,
      0.468,
      0.48100000000000004,
      0.49400000000000005,
      0.507,
      0.52,
      0.533,
      0.546,
      0.559,
      0.5720000000000001,
      0.5850000000000001,
      0.5980000000000001,
      0.6110000000000001,
      0.6240000000000001,
      0.637,
      0.65
    ],
    "mean": 0.23438527724665392,
    "std": 0.07227784406778863,
    "skewness": 0.13567792791255065,
    "kurtosis": 0.3541304703199524
  },
  "emotion_shame": {
    "histogram": [
      49,
      2,
      14,
      0,
      733,
      17,
      42,
      1,
      2115,
      2,
      100,
      1,
      2888,
      6,
      25,
      44,
      2652,
      1,
      28,
      18,
      1081,
      0,
      6,
      6,
      0,
      481,
      0,
      1,
      0,
      93,
      0,
      3,
      0,
      35,
      0,
      0,
      0,
      7,
      0,
      0,
      0,
      3,
      0,
      0,
      0,
      4,
      0,
      0,
      0,
      2
    ],
    "bins": [
      0.0,
      0.012,
      0.024,
      0.036000000000000004,
      0.048,
      0.06,
      0.07200000000000001,
      0.084,
      0.096,
      0.108,
      0.12,
      0.132,
      0.14400000000000002,
      0.156,
      0.168,
      0.18,
      0.192,
      0.20400000000000001,
      0.216,
      0.228,
      0.24,
      0.252,
      0.264,
      0.276,
      0.28800000000000003,
      0.3,
      0.312,
      0.324,
      0.336,
      0.34800000000000003,
      0.36,
      0.372,
      0.384,
      0.396,
      0.40800000000000003,
      0.42,
      0.432,
      0.444,
      0.456,
      0.468,
      0.48,
      0.492,
      0.504,
      0.516,
      0.528,
      0.54,
      0.552,
      0.5640000000000001,
      0.5760000000000001,
      0.588,
      0.6
    ],
    "mean": 0.16509990439770555,
    "std": 0.06835304441412392,
    "skewness": 0.5093605044406724,
    "kurtosis": 0.9421935573611449
  },
  "emotion_fear": {
    "histogram": [
      5,
      9,
      4,
      0,
      653,
      15,
      18,
      0,
      3752,
      0,
      51,
      0,
      3144,
      0,
      0,
      40,
      2029,
      0,
      3,
      3,
      292,
      0,
      0,
      1,
      0,
      327,
      0,
      0,
      0,
      24,
      0,
      0,
      0,
      73,
      0,
      0,
      0,
      5,
      0,
      0,
      0,
      11,
      0,
      0,
      0,
      0,
      0,
      0,
      0,
      1
    ],
    "bins": [
      0.0,
      0.012,
      0.024,
      0.036000000000000004,
      0.048,
      0.06,
      0.07200000000000001,
      0.084,
      0.096,
      0.108,
      0.12,
      0.132,
      0.14400000000000002,
      0.156,
      0.168,
      0.18,
      0.192,
      0.20400000000000001,
      0.216,
      0.228,
      0.24,
      0.252,
      0.264,
      0.276,
      0.28800000000000003,
      0.3,
      0.312,
      0.324,
      0.336,
      0.34800000000000003,
      0.36,
      0.372,
      0.384,
      0.396,
      0.40800000000000003,
      0.42,
      0.432,
      0.444,
      0.456,
      0.468,
      0.48,
      0.492,
      0.504,
      0.516,
      0.528,
      0.54,
      0.552,
      0.5640000000000001,
      0.5760000000000001,
      0.588,
      0.6
    ],
    "mean": 0.14533795411089867,
    "std": 0.06120451277134101,
    "skewness": 1.2736829656291109,
    "kurtosis": 3.3059693090003694
  },
  "bentham_intensity": {
    "histogram": [
      1,
      0,
      0,
      0,
      0,
      0,
      13,
      0,
      0,
      0,
      0,
      0,
      557,
      0,
      0,
      5,
      0,
      0,
      2549,
      0,
      0,
      69,
      0,
      0,
      0,
      43,
      0,
      0,
      0,
      0,
      0,
      3315,
      0,
      0,
      533,
      0,
      0,
      2444,
      1,
      0,
      216,
      0,
      3,
      581,
      0,
      1,
      123,
      0,
      0,
      6
    ],
    "bins": [
      0.1,
      0.116,
      0.132,
      0.14800000000000002,
      0.164,
      0.18,
      0.196,
      0.21200000000000002,
      0.228,
      0.24400000000000002,
      0.26,
      0.276,
      0.29200000000000004,
      0.30800000000000005,
      0.324,
      0.33999999999999997,
      0.356,
      0.372,
      0.388,
      0.404,
      0.42000000000000004,
      0.43600000000000005,
      0.45199999999999996,
      0.46799999999999997,
      0.484,
      0.5,
      0.516,
      0.532,
      0.548,
      0.5640000000000001,
      0.58,
      0.596,
      0.612,
      0.628,
      0.644,
      0.66,
      0.676,
      0.692,
      0.708,
      0.724,
      0.74,
      0.756,
      0.772,
      0.788,
      0.8039999999999999,
      0.82,
      0.836,
      0.852,
      0.868,
      0.884,
      0.9
    ],
    "mean": 0.5765372848948375,
    "std": 0.14277259340711107,
    "skewness": -0.38097945136667266,
    "kurtosis": -0.9131849523107025
  },
  "bentham_duration": {
    "histogram": [
      5,
      0,
      0,
      0,
      0,
      194,
      0,
      0,
      1,
      0,
      0,
      1226,
      0,
      0,
      0,
      0,
      0,
      1167,
      0,
      0,
      20,
      0,
      0,
      254,
      0,
      0,
      0,
      0,
      0,
      1245,
      0,
      0,
      27,
      0,
      0,
      2696,
      0,
      0,
      34,
      0,
      0,
      2929,
      0,
      0,
      197,
      0,
      0,
      462,
      0,
      3
    ],
    "bins": [
      0.1,
      0.117,
      0.134,
      0.15100000000000002,
      0.168,
      0.185,
      0.202,
      0.21900000000000003,
      0.23600000000000002,
      0.253,
      0.27,
      0.28700000000000003,
      0.30400000000000005,
      0.32100000000000006,
      0.338,
      0.355,
      0.372,
      0.389,
      0.406,
      0.42300000000000004,
      0.44000000000000006,
      0.4570000000000001,
      0.474,
      0.491,
      0.508,
      0.525,
      0.542,
      0.559,
      0.5760000000000001,
      0.5930000000000001,
      0.61,
      0.627,
      0.644,
      0.661,
      0.678,
      0.6950000000000001,
      0.7120000000000001,
      0.729,
      0.746,
      0.763,
      0.78,
      0.797,
      0.8140000000000001,
      0.8310000000000001,
      0.848,
      0.865,
      0.882,
      0.899,
      0.916,
      0.933,
      0.95
    ],
    "mean": 0.6325717017208413,
    "std": 0.19073617600213832,
    "skewness": -0.7090189586857025,
    "kurtosis": -0.7659664599291043
  },
  "bentham_certainty": {
    "histogram": [
      1,
      0,
      1,
      0,
      0,
      67,
      0,
      0,
      5,
      0,
      0,
      681,
      0,
      16,
      0,
      0,
      1021,
      0,
      0,
      62,
      0,
      0,
      773,
      0,
      0,
      21,
      0,
      1926,
      0,
      0,
      42,
      0,
      0,
      2217,
      0,
      0,
      58,
      0,
      2561,
      6,
      0,
      162,
      0,
      0,
      805,
      0,
      0,
      27,
      0,
      8
    ],
    "bins": [
      0.1,
      0.11800000000000001,
      0.136,
      0.15400000000000003,
      0.17200000000000001,
      0.19,
      0.20800000000000002,
      0.226,
      0.24400000000000002,
      0.262,
      0.28,
      0.29800000000000004,
      0.31600000000000006,
      0.3340000000000001,
      0.352,
      0.37,
      0.388,
      0.406,
      0.42400000000000004,
      0.44200000000000006,
      0.4600000000000001,
      0.4780000000000001,
      0.496,
      0.514,
      0.532,
      0.55,
      0.5680000000000001,
      0.5860000000000001,
      0.604,
      0.622,
      0.64,
      0.658,
      0.676,
      0.6940000000000001,
      0.7120000000000001,
      0.7300000000000001,
      0.7480000000000001,
      0.766,
      0.784,
      0.802,
      0.8200000000000001,
      0.8380000000000001,
      0.8560000000000001,
      0.8740000000000001,
      0.892,
      0.91,
      0.928,
      0.9460000000000001,
      0.9640000000000001,
      0.9820000000000001,
      1.0
    ],
    "mean": 0.6488546845124283,
    "std": 0.17287349874932695,
    "skewness": -0.5669516469019356,
    "kurtosis": -0.5602895179497231
  },
  "bentham_propinquity": {
    "histogram": [
      16,
      0,
      0,
      0,
      0,
      0,
      234,
      0,
      0,
      0,
      0,
      0,
      304,
      0,
      0,
      2,
      0,
      0,
      29,
      0,
      0,
      0,
      0,
      0,
      294,
      0,
      0,
      0,
      7,
      0,
      0,
      382,
      0,
      0,
      0,
      0,
      0,
      2630,
      0,
      0,
      78,
      0,
      0,
      6335,
      0,
      0,
      101,
      0,
      0,
      48
    ],
    "bins": [
      0.2,
      0.21600000000000003,
      0.232,
      0.248,
      0.264,
      0.28,
      0.29600000000000004,
      0.312,
      0.328,
      0.34400000000000003,
      0.36,
      0.376,
      0.392,
      0.40800000000000003,
      0.42400000000000004,
      0.44,
      0.456,
      0.47200000000000003,
      0.48800000000000004,
      0.504,
      0.52,
      0.536,
      0.552,
      0.5680000000000001,
      0.5840000000000001,
      0.6000000000000001,
      0.6160000000000001,
      0.632,
      0.648,
      0.664,
      0.6799999999999999,
      0.696,
      0.712,
      0.728,
      0.744,
      0.76,
      0.776,
      0.792,
      0.808,
      0.8240000000000001,
      0.8400000000000001,
      0.8560000000000001,
      0.8720000000000001,
      0.8880000000000001,
      0.9039999999999999,
      0.9199999999999999,
      0.9359999999999999,
      0.952,
      0.968,
      0.984,
      1.0
    ],
    "mean": 0.8293021032504782,
    "std": 0.13486375298567554,
    "skewness": -2.5608702984497644,
    "kurtosis": 6.4597407264566105
  },
  "surd_selection": {
    "histogram": [
      13,
      0,
      8,
      0,
      0,
      252,
      0,
      0,
      10,
      0,
      0,
      1277,
      0,
      19,
      0,
      0,
      1997,
      0,
      0,
      22,
      0,
      0,
      55,
      0,
      0,
      1,
      0,
      2506,
      0,
      0,
      79,
      0,
      0,
      2580,
      0,
      0,
      28,
      0,
      1540,
      0,
      0,
      30,
      0,
      0,
      40,
      0,
      0,
      0,
      0,
      3
    ],
    "bins": [
      0.1,
      0.11800000000000001,
      0.136,
      0.15400000000000003,
      0.17200000000000001,
      0.19,
      0.20800000000000002,
      0.226,
      0.24400000000000002,
      0.262,
      0.28,
      0.29800000000000004,
      0.31600000000000006,
      0.3340000000000001,
      0.352,
      0.37,
      0.388,
      0.406,
      0.42400000000000004,
      0.44200000000000006,
      0.4600000000000001,
      0.4780000000000001,
      0.496,
      0.514,
      0.532,
      0.55,
      0.5680000000000001,
      0.5860000000000001,
      0.604,
      0.622,
      0.64,
      0.658,
      0.676,
      0.6940000000000001,
      0.7120000000000001,
      0.7300000000000001,
      0.7480000000000001,
      0.766,
      0.784,
      0.802,
      0.8200000000000001,
      0.8380000000000001,
      0.8560000000000001,
      0.8740000000000001,
      0.892,
      0.91,
      0.928,
      0.9460000000000001,
      0.9640000000000001,
      0.9820000000000001,
      1.0
    ],
    "mean": 0.5698231357552581,
    "std": 0.177112265441723,
    "skewness": -0.3967194934204401,
    "kurtosis": -1.0527919478694365
  },
  "surd_uncertainty": {
    "histogram": [
      3,
      0,
      0,
      2,
      0,
      0,
      140,
      0,
      0,
      7,
      0,
      0,
      1325,
      0,
      0,
      15,
      0,
      0,
      2568,
      0,
      0,
      54,
      0,
      0,
      0,
      626,
      0,
      0,
      4,
      0,
      0,
      1846,
      0,
      0,
      51,
      0,
      0,
      2234,
      0,
      0,
      87,
      0,
      0,
      1446,
      0,
      0,
      45,
      0,
      0,
      7
    ],
    "bins": [
      0.1,
      0.116,
      0.132,
      0.14800000000000002,
      0.164,
      0.18,
      0.196,
      0.21200000000000002,
      0.228,
      0.24400000000000002,
      0.26,
      0.276,
      0.29200000000000004,
      0.30800000000000005,
      0.324,
      0.33999999999999997,
      0.356,
      0.372,
      0.388,
      0.404,
      0.42000000000000004,
      0.43600000000000005,
      0.45199999999999996,
      0.46799999999999997,
      0.484,
      0.5,
      0.516,
      0.532,
      0.548,
      0.5640000000000001,
      0.58,
      0.596,
      0.612,
      0.628,
      0.644,
      0.66,
      0.676,
      0.692,
      0.708,
      0.724,
      0.74,
      0.756,
      0.772,
      0.788,
      0.8039999999999999,
      0.82,
      0.836,
      0.852,
      0.868,
      0.884,
      0.9
    ],
    "mean": 0.5517160611854686,
    "std": 0.17384601675961847,
    "skewness": -0.09491732238216777,
    "kurtosis": -1.2964479454108904
  },
  "surd_risk": {
    "histogram": [
      28,
      0,
      0,
      4,
      0,
      0,
      372,
      0,
      0,
      5,
      0,
      0,
      1219,
      0,
      0,
      10,
      0,
      0,
      1359,
      0,
      0,
      41,
      0,
      0,
      0,
      2282,
      0,
      0,
      33,
      0,
      0,
      1663,
      0,
      0,
      80,
      0,
      0,
      1695,
      0,
      0,
      139,
      0,
      0,
      1201,
      0,
      0,
      143,
      0,
      0,
      186
    ],
    "bins": [
      0.1,
      0.116,
      0.132,
      0.14800000000000002,
      0.164,
      0.18,
      0.196,
      0.21200000000000002,
      0.228,
      0.24400000000000002,
      0.26,
      0.276,
      0.29200000000000004,
      0.30800000000000005,
      0.324,
      0.33999999999999997,
      0.356,
      0.372,
      0.388,
      0.404,
      0.42000000000000004,
      0.43600000000000005,
      0.45199999999999996,
      0.46799999999999997,
      0.484,
      0.5,
      0.516,
      0.532,
      0.548,
      0.5640000000000001,
      0.58,
      0.596,
      0.612,
      0.628,
      0.644,
      0.66,
      0.676,
      0.692,
      0.708,
      0.724,
      0.74,
      0.756,
      0.772,
      0.788,
      0.8039999999999999,
      0.82,
      0.836,
      0.852,
      0.868,
      0.884,
      0.9
    ],
    "mean": 0.5506453154875717,
    "std": 0.17626303136411017,
    "skewness": -0.10193525940293845,
    "kurtosis": -0.8100136373444209
  },
  "surd_decision": {
    "histogram": [
      46,
      0,
      0,
      1,
      0,
      0,
      277,
      0,
      0,
      8,
      0,
      0,
      596,
      0,
      0,
      6,
      0,
      0,
      1816,
      0,
      0,
      25,
      0,
      0,
      1586,
      0,
      0,
      0,
      62,
      0,
      0,
      2261,
      0,
      0,
      166,
      0,
      0,
      2210,
      0,
      0,
      343,
      0,
      0,
      1019,
      0,
      0,
      37,
      0,
      0,
      1
    ],
    "bins": [
      0.2,
      0.21600000000000003,
      0.232,
      0.248,
      0.264,
      0.28,
      0.29600000000000004,
      0.312,
      0.328,
      0.34400000000000003,
      0.36,
      0.376,
      0.392,
      0.40800000000000003,
      0.42400000000000004,
      0.44,
      0.456,
      0.47200000000000003,
      0.48800000000000004,
      0.504,
      0.52,
      0.536,
      0.552,
      0.5680000000000001,
      0.5840000000000001,
      0.6000000000000001,
      0.6160000000000001,
      0.632,
      0.648,
      0.664,
      0.6799999999999999,
      0.696,
      0.712,
      0.728,
      0.744,
      0.76,
      0.776,
      0.792,
      0.808,
      0.8240000000000001,
      0.8400000000000001,
      0.8560000000000001,
      0.8720000000000001,
      0.8880000000000001,
      0.9039999999999999,
      0.9199999999999999,
      0.9359999999999999,
      0.952,
      0.968,
      0.984,
      1.0
    ],
    "mean": 0.666357552581262,
    "std": 0.15820190126359862,
    "skewness": -0.41863958348330577,
    "kurtosis": -0.5412588791733932
  }
}